g3visu/__init__.py
g3visu/_cli.py
g3visu/meta/__init__.py
g3visu/meta/_meta.py
g3visu/site/__init__.py
g3visu/site/_site_svg.py
g3visu/site/_table.py
g3visu/site/site.svg
g3visu/typeinfo/__init__.py
g3visu/typeinfo/_list_operations.py
g3visu/typeinfo/_typeinfo.py
g3visu/typeinfo/py.typed
g3visu/utils/__init__.py
g3visu/utils/_download_from_sites.py
g3visu-0.1.12.dist-info/LICENCE
g3visu-0.1.12.dist-info/METADATA
g3visu-0.1.12.dist-info/WHEEL
g3visu-0.1.12.dist-info/entry_points.txt
g3visu-0.1.12.dist-info/top_level.txt
g3visu-0.1.12.dist-info/RECORD
